ktreediff/__init__.py
ktreediff/__main__.py
ktreediff/file.py
ktreediff/node.py
ktreediff/util.py
ktreediff/version.py
ktreediff-0.1.0.dist-info/LICENSE
ktreediff-0.1.0.dist-info/METADATA
ktreediff-0.1.0.dist-info/WHEEL
ktreediff-0.1.0.dist-info/entry_points.txt
ktreediff-0.1.0.dist-info/top_level.txt
ktreediff-0.1.0.dist-info/RECORD
